dataci/__init__.py
dataci/config.py
dataci/utils.py
dataci/command/__init__.py
dataci/command/benchmark.py
dataci/command/connect.py
dataci/command/dataset.py
dataci/command/stage.py
dataci/command/utils.py
dataci/command/workflow.py
dataci/command/workspace.py
dataci/connector/__init__.py
dataci/connector/s3.py
dataci/db/__init__.py
dataci/db/benchmark.py
dataci/db/dataset.py
dataci/db/init.py
dataci/db/run.py
dataci/db/stage.py
dataci/db/workflow.py
dataci/decorators/__init__.py
dataci/decorators/base.py
dataci/decorators/event.py
dataci/function_zoo/__init__.py
dataci/function_zoo/benchmark/__init__.py
dataci/function_zoo/benchmark/text_classification.py
dataci/function_zoo/data_debugger/__init__.py
dataci/function_zoo/data_debugger/auto_pipeline_selection.py
dataci/function_zoo/data_debugger/data_flow_trace.py
dataci/function_zoo/data_debugger/data_investigator/__init__.py
dataci/function_zoo/data_debugger/data_investigator/bias_analysis.py
dataci/function_zoo/data_debugger/data_investigator/interactive_compare.py
dataci/function_zoo/data_debugger/data_investigator/sample_visualize.py
dataci/function_zoo/data_debugger/data_investigator/statistical_analysis.py
dataci/function_zoo/data_selection/__init__.py
dataci/function_zoo/data_selection/alaas.py
dataci/models/__init__.py
dataci/models/base.py
dataci/models/dataset.py
dataci/models/event.py
dataci/models/stage.py
dataci/models/workflow.py
dataci/models/workspace.py
dataci/models/run/__init__.py
dataci/models/run/list.py
dataci/models/run/run.py
dataci/models/run/save.py
dataci/plugins/__init__.py
dataci/plugins/decorators/__init__.py
dataci/plugins/decorators/airflow.py
dataci/plugins/orchestrator/__init__.py
dataci/plugins/orchestrator/airflow.py
dataci/plugins/orchestrator/script.py
dataci/server/__init__.py
dataci/server/server.py
dataci/server/trigger.py
example/ci/build_text_dataset.py
example/ci/config_ci.py
example/ci/sentiment_analysis_airflow.py
ml_data_ci-0.0.2.dist-info/LICENSE
ml_data_ci-0.0.2.dist-info/METADATA
ml_data_ci-0.0.2.dist-info/WHEEL
ml_data_ci-0.0.2.dist-info/entry_points.txt
ml_data_ci-0.0.2.dist-info/top_level.txt
ml_data_ci-0.0.2.dist-info/RECORD
