Metadata-Version: 2.1
Name: ml-data-ci
Version: 0.0.2
Summary: A platform for tracking data-centric AI pipelines in dynamic streaming data
Home-page: https://github.com/MLSysOps/DataCI
Author: Yuanming Li
Author-email: yuanmingleee@gmail.com
License: MIT
Keywords: Data-centric AI,Streaming Data,MLOps,Pipeline Tracking,Data Versioning
Classifier: Development Status :: 3 - Alpha
Classifier: Intended Audience :: Education
Classifier: Intended Audience :: Financial and Insurance Industry
Classifier: Intended Audience :: Science/Research
Classifier: Intended Audience :: Developers
Classifier: Intended Audience :: Information Technology
Classifier: License :: OSI Approved :: MIT License
Classifier: Programming Language :: Python :: 3
Classifier: Operating System :: POSIX :: Linux
License-File: LICENSE
Requires-Dist: unidecode (>=1.3.6)
Requires-Dist: augly[text] (>=1.0.0)
Requires-Dist: numpy (>=1.21.6)
Requires-Dist: pandas (>=1.3.5)
Requires-Dist: requests (==2.30.0)
Requires-Dist: fastapi (>=0.95.1)
Requires-Dist: networkx (>=3.1)
Requires-Dist: uvicorn (>=0.15.0)
Requires-Dist: click (==8.1.3)
Requires-Dist: tqdm (>=4.62.3)
